[{"glyph_id":25866,"page_number":161,"line_number":1,"sura_number":7,"ayah_number":82,"position":1,"min_x":923.0,"min_y":39.0,"max_x":980.0,"max_y":97.0},{"glyph_id":25867,"page_number":161,"line_number":1,"sura_number":7,"ayah_number":82,"position":2,"min_x":752.0,"min_y":39.0,"max_x":916.0,"max_y":94.0},{"glyph_id":25868,"page_number":161,"line_number":1,"sura_number":7,"ayah_number":82,"position":3,"min_x":629.0,"min_y":36.0,"max_x":741.0,"max_y":97.0},{"glyph_id":25869,"page_number":161,"line_number":1,"sura_number":7,"ayah_number":82,"position":4,"min_x":518.0,"min_y":32.0,"max_x":621.0,"max_y":99.0},{"glyph_id":25870,"page_number":161,"line_number":1,"sura_number":7,"ayah_number":82,"position":5,"min_x":450.0,"min_y":24.0,"max_x":508.0,"max_y":102.0},{"glyph_id":25871,"page_number":161,"line_number":1,"sura_number":7,"ayah_number":82,"position":6,"min_x":408.0,"min_y":28.0,"max_x":444.0,"max_y":92.0},{"glyph_id":25872,"page_number":161,"line_number":1,"sura_number":7,"ayah_number":82,"position":7,"min_x":304.0,"min_y":32.0,"max_x":399.0,"max_y":99.0},{"glyph_id":25873,"page_number":161,"line_number":1,"sura_number":7,"ayah_number":82,"position":8,"min_x":122.0,"min_y":29.0,"max_x":291.0,"max_y":109.0},{"glyph_id":25874,"page_number":161,"line_number":1,"sura_number":7,"ayah_number":82,"position":9,"min_x":52.0,"min_y":47.0,"max_x":111.0,"max_y":99.0},{"glyph_id":25875,"page_number":161,"line_number":2,"sura_number":7,"ayah_number":82,"position":10,"min_x":788.0,"min_y":140.0,"max_x":982.0,"max_y":213.0},{"glyph_id":25876,"page_number":161,"line_number":2,"sura_number":7,"ayah_number":82,"position":11,"min_x":778.0,"min_y":132.0,"max_x":777.0,"max_y":154.0},{"glyph_id":25877,"page_number":161,"line_number":2,"sura_number":7,"ayah_number":82,"position":12,"min_x":687.0,"min_y":139.0,"max_x":773.0,"max_y":220.0},{"glyph_id":25878,"page_number":161,"line_number":2,"sura_number":7,"ayah_number":82,"position":13,"min_x":583.0,"min_y":132.0,"max_x":676.0,"max_y":205.0},{"glyph_id":25879,"page_number":161,"line_number":2,"sura_number":7,"ayah_number":82,"position":14,"min_x":414.0,"min_y":143.0,"max_x":572.0,"max_y":205.0},{"glyph_id":25880,"page_number":161,"line_number":2,"sura_number":7,"ayah_number":82,"position":15,"min_x":316.0,"min_y":135.0,"max_x":398.0,"max_y":211.0},{"glyph_id":25881,"page_number":161,"line_number":2,"sura_number":7,"ayah_number":83,"position":1,"min_x":165.0,"min_y":130.0,"max_x":317.0,"max_y":205.0},{"glyph_id":25882,"page_number":161,"line_number":2,"sura_number":7,"ayah_number":83,"position":2,"min_x":50.0,"min_y":135.0,"max_x":157.0,"max_y":204.0},{"glyph_id":25883,"page_number":161,"line_number":3,"sura_number":7,"ayah_number":83,"position":3,"min_x":931.0,"min_y":240.0,"max_x":982.0,"max_y":317.0},{"glyph_id":25884,"page_number":161,"line_number":3,"sura_number":7,"ayah_number":83,"position":4,"min_x":788.0,"min_y":244.0,"max_x":919.0,"max_y":317.0},{"glyph_id":25885,"page_number":161,"line_number":3,"sura_number":7,"ayah_number":83,"position":5,"min_x":697.0,"min_y":248.0,"max_x":778.0,"max_y":304.0},{"glyph_id":25886,"page_number":161,"line_number":3,"sura_number":7,"ayah_number":83,"position":6,"min_x":585.0,"min_y":254.0,"max_x":680.0,"max_y":313.0},{"glyph_id":25887,"page_number":161,"line_number":3,"sura_number":7,"ayah_number":83,"position":7,"min_x":432.0,"min_y":247.0,"max_x":574.0,"max_y":320.0},{"glyph_id":25888,"page_number":161,"line_number":3,"sura_number":7,"ayah_number":83,"position":8,"min_x":343.0,"min_y":242.0,"max_x":425.0,"max_y":318.0},{"glyph_id":25889,"page_number":161,"line_number":3,"sura_number":7,"ayah_number":84,"position":1,"min_x":170.0,"min_y":242.0,"max_x":344.0,"max_y":315.0},{"glyph_id":25890,"page_number":161,"line_number":3,"sura_number":7,"ayah_number":84,"position":2,"min_x":56.0,"min_y":248.0,"max_x":167.0,"max_y":328.0},{"glyph_id":25891,"page_number":161,"line_number":4,"sura_number":7,"ayah_number":84,"position":3,"min_x":882.0,"min_y":354.0,"max_x":980.0,"max_y":419.0},{"glyph_id":25892,"page_number":161,"line_number":4,"sura_number":7,"ayah_number":84,"position":4,"min_x":870.0,"min_y":340.0,"max_x":869.0,"max_y":361.0},{"glyph_id":25893,"page_number":161,"line_number":4,"sura_number":7,"ayah_number":84,"position":5,"min_x":752.0,"min_y":351.0,"max_x":865.0,"max_y":419.0},{"glyph_id":25894,"page_number":161,"line_number":4,"sura_number":7,"ayah_number":84,"position":6,"min_x":603.0,"min_y":357.0,"max_x":752.0,"max_y":418.0},{"glyph_id":25895,"page_number":161,"line_number":4,"sura_number":7,"ayah_number":84,"position":7,"min_x":491.0,"min_y":357.0,"max_x":590.0,"max_y":416.0},{"glyph_id":25896,"page_number":161,"line_number":4,"sura_number":7,"ayah_number":84,"position":8,"min_x":369.0,"min_y":348.0,"max_x":484.0,"max_y":421.0},{"glyph_id":25897,"page_number":161,"line_number":4,"sura_number":7,"ayah_number":84,"position":9,"min_x":153.0,"min_y":353.0,"max_x":357.0,"max_y":429.0},{"glyph_id":25898,"page_number":161,"line_number":4,"sura_number":7,"ayah_number":84,"position":10,"min_x":52.0,"min_y":349.0,"max_x":136.0,"max_y":425.0},{"glyph_id":25899,"page_number":161,"line_number":5,"sura_number":7,"ayah_number":85,"position":1,"min_x":898.0,"min_y":461.0,"max_x":982.0,"max_y":534.0},{"glyph_id":25900,"page_number":161,"line_number":5,"sura_number":7,"ayah_number":85,"position":2,"min_x":752.0,"min_y":467.0,"max_x":887.0,"max_y":525.0},{"glyph_id":25901,"page_number":161,"line_number":5,"sura_number":7,"ayah_number":85,"position":3,"min_x":631.0,"min_y":453.0,"max_x":740.0,"max_y":543.0},{"glyph_id":25902,"page_number":161,"line_number":5,"sura_number":7,"ayah_number":85,"position":4,"min_x":502.0,"min_y":459.0,"max_x":621.0,"max_y":525.0},{"glyph_id":25903,"page_number":161,"line_number":5,"sura_number":7,"ayah_number":85,"position":5,"min_x":493.0,"min_y":445.0,"max_x":494.0,"max_y":466.0},{"glyph_id":25904,"page_number":161,"line_number":5,"sura_number":7,"ayah_number":85,"position":6,"min_x":429.0,"min_y":459.0,"max_x":490.0,"max_y":519.0},{"glyph_id":25905,"page_number":161,"line_number":5,"sura_number":7,"ayah_number":85,"position":7,"min_x":306.0,"min_y":461.0,"max_x":419.0,"max_y":530.0},{"glyph_id":25906,"page_number":161,"line_number":5,"sura_number":7,"ayah_number":85,"position":8,"min_x":127.0,"min_y":461.0,"max_x":288.0,"max_y":526.0},{"glyph_id":25907,"page_number":161,"line_number":5,"sura_number":7,"ayah_number":85,"position":9,"min_x":51.0,"min_y":463.0,"max_x":109.0,"max_y":515.0},{"glyph_id":25908,"page_number":161,"line_number":6,"sura_number":7,"ayah_number":85,"position":10,"min_x":948.0,"min_y":577.0,"max_x":985.0,"max_y":622.0},{"glyph_id":25909,"page_number":161,"line_number":6,"sura_number":7,"ayah_number":85,"position":11,"min_x":801.0,"min_y":568.0,"max_x":939.0,"max_y":644.0},{"glyph_id":25910,"page_number":161,"line_number":6,"sura_number":7,"ayah_number":85,"position":12,"min_x":739.0,"min_y":574.0,"max_x":789.0,"max_y":633.0},{"glyph_id":25911,"page_number":161,"line_number":6,"sura_number":7,"ayah_number":85,"position":13,"min_x":660.0,"min_y":566.0,"max_x":730.0,"max_y":638.0},{"glyph_id":25912,"page_number":161,"line_number":6,"sura_number":7,"ayah_number":85,"position":14,"min_x":560.0,"min_y":571.0,"max_x":650.0,"max_y":635.0},{"glyph_id":25913,"page_number":161,"line_number":6,"sura_number":7,"ayah_number":85,"position":15,"min_x":559.0,"min_y":548.0,"max_x":554.0,"max_y":570.0},{"glyph_id":25914,"page_number":161,"line_number":6,"sura_number":7,"ayah_number":85,"position":16,"min_x":504.0,"min_y":568.0,"max_x":550.0,"max_y":624.0},{"glyph_id":25915,"page_number":161,"line_number":6,"sura_number":7,"ayah_number":85,"position":17,"min_x":295.0,"min_y":568.0,"max_x":498.0,"max_y":644.0},{"glyph_id":25916,"page_number":161,"line_number":6,"sura_number":7,"ayah_number":85,"position":18,"min_x":157.0,"min_y":560.0,"max_x":283.0,"max_y":643.0},{"glyph_id":25917,"page_number":161,"line_number":6,"sura_number":7,"ayah_number":85,"position":19,"min_x":52.0,"min_y":581.0,"max_x":154.0,"max_y":635.0},{"glyph_id":25918,"page_number":161,"line_number":7,"sura_number":7,"ayah_number":85,"position":20,"min_x":811.0,"min_y":672.0,"max_x":979.0,"max_y":755.0},{"glyph_id":25919,"page_number":161,"line_number":7,"sura_number":7,"ayah_number":85,"position":21,"min_x":797.0,"min_y":658.0,"max_x":799.0,"max_y":679.0},{"glyph_id":25920,"page_number":161,"line_number":7,"sura_number":7,"ayah_number":85,"position":22,"min_x":689.0,"min_y":667.0,"max_x":795.0,"max_y":741.0},{"glyph_id":25921,"page_number":161,"line_number":7,"sura_number":7,"ayah_number":85,"position":23,"min_x":490.0,"min_y":673.0,"max_x":674.0,"max_y":743.0},{"glyph_id":25922,"page_number":161,"line_number":7,"sura_number":7,"ayah_number":85,"position":24,"min_x":262.0,"min_y":673.0,"max_x":473.0,"max_y":744.0},{"glyph_id":25923,"page_number":161,"line_number":7,"sura_number":7,"ayah_number":85,"position":25,"min_x":187.0,"min_y":672.0,"max_x":245.0,"max_y":739.0},{"glyph_id":25924,"page_number":161,"line_number":7,"sura_number":7,"ayah_number":85,"position":26,"min_x":51.0,"min_y":676.0,"max_x":186.0,"max_y":745.0},{"glyph_id":25925,"page_number":161,"line_number":8,"sura_number":7,"ayah_number":85,"position":27,"min_x":852.0,"min_y":780.0,"max_x":982.0,"max_y":844.0},{"glyph_id":25926,"page_number":161,"line_number":8,"sura_number":7,"ayah_number":85,"position":28,"min_x":645.0,"min_y":777.0,"max_x":843.0,"max_y":863.0},{"glyph_id":25927,"page_number":161,"line_number":8,"sura_number":7,"ayah_number":85,"position":29,"min_x":569.0,"min_y":782.0,"max_x":630.0,"max_y":847.0},{"glyph_id":25928,"page_number":161,"line_number":8,"sura_number":7,"ayah_number":85,"position":30,"min_x":404.0,"min_y":776.0,"max_x":565.0,"max_y":850.0},{"glyph_id":25929,"page_number":161,"line_number":8,"sura_number":7,"ayah_number":85,"position":31,"min_x":302.0,"min_y":798.0,"max_x":391.0,"max_y":853.0},{"glyph_id":25930,"page_number":161,"line_number":8,"sura_number":7,"ayah_number":85,"position":32,"min_x":161.0,"min_y":773.0,"max_x":292.0,"max_y":851.0},{"glyph_id":25931,"page_number":161,"line_number":8,"sura_number":7,"ayah_number":85,"position":33,"min_x":52.0,"min_y":785.0,"max_x":146.0,"max_y":847.0},{"glyph_id":25932,"page_number":161,"line_number":9,"sura_number":7,"ayah_number":85,"position":34,"min_x":807.0,"min_y":892.0,"max_x":984.0,"max_y":960.0},{"glyph_id":25933,"page_number":161,"line_number":9,"sura_number":7,"ayah_number":85,"position":35,"min_x":794.0,"min_y":872.0,"max_x":797.0,"max_y":892.0},{"glyph_id":25934,"page_number":161,"line_number":9,"sura_number":7,"ayah_number":85,"position":36,"min_x":624.0,"min_y":890.0,"max_x":793.0,"max_y":968.0},{"glyph_id":25935,"page_number":161,"line_number":9,"sura_number":7,"ayah_number":85,"position":37,"min_x":542.0,"min_y":889.0,"max_x":614.0,"max_y":957.0},{"glyph_id":25936,"page_number":161,"line_number":9,"sura_number":7,"ayah_number":85,"position":38,"min_x":454.0,"min_y":880.0,"max_x":538.0,"max_y":973.0},{"glyph_id":25937,"page_number":161,"line_number":9,"sura_number":7,"ayah_number":85,"position":39,"min_x":397.0,"min_y":902.0,"max_x":439.0,"max_y":963.0},{"glyph_id":25938,"page_number":161,"line_number":9,"sura_number":7,"ayah_number":85,"position":40,"min_x":215.0,"min_y":888.0,"max_x":388.0,"max_y":948.0},{"glyph_id":25939,"page_number":161,"line_number":9,"sura_number":7,"ayah_number":85,"position":41,"min_x":50.0,"min_y":886.0,"max_x":213.0,"max_y":957.0},{"glyph_id":25940,"page_number":161,"line_number":10,"sura_number":7,"ayah_number":85,"position":42,"min_x":898.0,"min_y":991.0,"max_x":980.0,"max_y":1067.0},{"glyph_id":25941,"page_number":161,"line_number":10,"sura_number":7,"ayah_number":86,"position":1,"min_x":822.0,"min_y":997.0,"max_x":899.0,"max_y":1064.0},{"glyph_id":25942,"page_number":161,"line_number":10,"sura_number":7,"ayah_number":86,"position":2,"min_x":673.0,"min_y":994.0,"max_x":819.0,"max_y":1058.0},{"glyph_id":25943,"page_number":161,"line_number":10,"sura_number":7,"ayah_number":86,"position":3,"min_x":514.0,"min_y":994.0,"max_x":666.0,"max_y":1068.0},{"glyph_id":25944,"page_number":161,"line_number":10,"sura_number":7,"ayah_number":86,"position":4,"min_x":398.0,"min_y":1003.0,"max_x":509.0,"max_y":1070.0},{"glyph_id":25945,"page_number":161,"line_number":10,"sura_number":7,"ayah_number":86,"position":5,"min_x":248.0,"min_y":993.0,"max_x":392.0,"max_y":1062.0},{"glyph_id":25946,"page_number":161,"line_number":10,"sura_number":7,"ayah_number":86,"position":6,"min_x":54.0,"min_y":989.0,"max_x":241.0,"max_y":1057.0},{"glyph_id":25947,"page_number":161,"line_number":11,"sura_number":7,"ayah_number":86,"position":7,"min_x":924.0,"min_y":1106.0,"max_x":982.0,"max_y":1170.0},{"glyph_id":25948,"page_number":161,"line_number":11,"sura_number":7,"ayah_number":86,"position":8,"min_x":797.0,"min_y":1113.0,"max_x":917.0,"max_y":1183.0},{"glyph_id":25949,"page_number":161,"line_number":11,"sura_number":7,"ayah_number":86,"position":9,"min_x":728.0,"min_y":1105.0,"max_x":787.0,"max_y":1171.0},{"glyph_id":25950,"page_number":161,"line_number":11,"sura_number":7,"ayah_number":86,"position":10,"min_x":660.0,"min_y":1107.0,"max_x":715.0,"max_y":1168.0},{"glyph_id":25951,"page_number":161,"line_number":11,"sura_number":7,"ayah_number":86,"position":11,"min_x":512.0,"min_y":1110.0,"max_x":648.0,"max_y":1169.0},{"glyph_id":25952,"page_number":161,"line_number":11,"sura_number":7,"ayah_number":86,"position":12,"min_x":445.0,"min_y":1127.0,"max_x":502.0,"max_y":1176.0},{"glyph_id":25953,"page_number":161,"line_number":11,"sura_number":7,"ayah_number":86,"position":13,"min_x":205.0,"min_y":1101.0,"max_x":439.0,"max_y":1171.0},{"glyph_id":25954,"page_number":161,"line_number":11,"sura_number":7,"ayah_number":86,"position":14,"min_x":57.0,"min_y":1103.0,"max_x":197.0,"max_y":1167.0},{"glyph_id":25955,"page_number":161,"line_number":11,"sura_number":7,"ayah_number":86,"position":15,"min_x":52.0,"min_y":1089.0,"max_x":54.0,"max_y":1110.0},{"glyph_id":25956,"page_number":161,"line_number":12,"sura_number":7,"ayah_number":86,"position":16,"min_x":764.0,"min_y":1209.0,"max_x":979.0,"max_y":1276.0},{"glyph_id":25957,"page_number":161,"line_number":12,"sura_number":7,"ayah_number":86,"position":17,"min_x":716.0,"min_y":1212.0,"max_x":749.0,"max_y":1282.0},{"glyph_id":25958,"page_number":161,"line_number":12,"sura_number":7,"ayah_number":86,"position":18,"min_x":540.0,"min_y":1206.0,"max_x":709.0,"max_y":1267.0},{"glyph_id":25959,"page_number":161,"line_number":12,"sura_number":7,"ayah_number":86,"position":19,"min_x":451.0,"min_y":1205.0,"max_x":535.0,"max_y":1280.0},{"glyph_id":25960,"page_number":161,"line_number":12,"sura_number":7,"ayah_number":86,"position":20,"min_x":212.0,"min_y":1194.0,"max_x":436.0,"max_y":1291.0},{"glyph_id":25961,"page_number":161,"line_number":12,"sura_number":7,"ayah_number":86,"position":21,"min_x":196.0,"min_y":1194.0,"max_x":198.0,"max_y":1216.0},{"glyph_id":25962,"page_number":161,"line_number":12,"sura_number":7,"ayah_number":86,"position":22,"min_x":54.0,"min_y":1204.0,"max_x":194.0,"max_y":1277.0},{"glyph_id":25963,"page_number":161,"line_number":13,"sura_number":7,"ayah_number":86,"position":23,"min_x":880.0,"min_y":1318.0,"max_x":982.0,"max_y":1386.0},{"glyph_id":25964,"page_number":161,"line_number":13,"sura_number":7,"ayah_number":86,"position":24,"min_x":764.0,"min_y":1314.0,"max_x":873.0,"max_y":1380.0},{"glyph_id":25965,"page_number":161,"line_number":13,"sura_number":7,"ayah_number":86,"position":25,"min_x":646.0,"min_y":1308.0,"max_x":760.0,"max_y":1383.0},{"glyph_id":25966,"page_number":161,"line_number":13,"sura_number":7,"ayah_number":86,"position":26,"min_x":449.0,"min_y":1311.0,"max_x":641.0,"max_y":1386.0},{"glyph_id":25967,"page_number":161,"line_number":13,"sura_number":7,"ayah_number":86,"position":27,"min_x":357.0,"min_y":1312.0,"max_x":439.0,"max_y":1388.0},{"glyph_id":25968,"page_number":161,"line_number":13,"sura_number":7,"ayah_number":87,"position":1,"min_x":271.0,"min_y":1324.0,"max_x":358.0,"max_y":1391.0},{"glyph_id":25969,"page_number":161,"line_number":13,"sura_number":7,"ayah_number":87,"position":2,"min_x":204.0,"min_y":1313.0,"max_x":265.0,"max_y":1377.0},{"glyph_id":25970,"page_number":161,"line_number":13,"sura_number":7,"ayah_number":87,"position":3,"min_x":52.0,"min_y":1305.0,"max_x":199.0,"max_y":1392.0},{"glyph_id":25971,"page_number":161,"line_number":14,"sura_number":7,"ayah_number":87,"position":4,"min_x":809.0,"min_y":1422.0,"max_x":974.0,"max_y":1500.0},{"glyph_id":25972,"page_number":161,"line_number":14,"sura_number":7,"ayah_number":87,"position":5,"min_x":683.0,"min_y":1425.0,"max_x":804.0,"max_y":1492.0},{"glyph_id":25973,"page_number":161,"line_number":14,"sura_number":7,"ayah_number":87,"position":6,"min_x":563.0,"min_y":1411.0,"max_x":671.0,"max_y":1496.0},{"glyph_id":25974,"page_number":161,"line_number":14,"sura_number":7,"ayah_number":87,"position":7,"min_x":419.0,"min_y":1410.0,"max_x":554.0,"max_y":1489.0},{"glyph_id":25975,"page_number":161,"line_number":14,"sura_number":7,"ayah_number":87,"position":8,"min_x":349.0,"min_y":1451.0,"max_x":411.0,"max_y":1495.0},{"glyph_id":25976,"page_number":161,"line_number":14,"sura_number":7,"ayah_number":87,"position":9,"min_x":191.0,"min_y":1417.0,"max_x":344.0,"max_y":1499.0},{"glyph_id":25977,"page_number":161,"line_number":14,"sura_number":7,"ayah_number":87,"position":10,"min_x":147.0,"min_y":1413.0,"max_x":183.0,"max_y":1489.0},{"glyph_id":25978,"page_number":161,"line_number":14,"sura_number":7,"ayah_number":87,"position":11,"min_x":59.0,"min_y":1427.0,"max_x":149.0,"max_y":1498.0},{"glyph_id":25979,"page_number":161,"line_number":15,"sura_number":7,"ayah_number":87,"position":12,"min_x":839.0,"min_y":1530.0,"max_x":983.0,"max_y":1602.0},{"glyph_id":25980,"page_number":161,"line_number":15,"sura_number":7,"ayah_number":87,"position":13,"min_x":762.0,"min_y":1529.0,"max_x":836.0,"max_y":1601.0},{"glyph_id":25981,"page_number":161,"line_number":15,"sura_number":7,"ayah_number":87,"position":14,"min_x":655.0,"min_y":1522.0,"max_x":756.0,"max_y":1613.0},{"glyph_id":25982,"page_number":161,"line_number":15,"sura_number":7,"ayah_number":87,"position":15,"min_x":585.0,"min_y":1532.0,"max_x":648.0,"max_y":1587.0},{"glyph_id":25983,"page_number":161,"line_number":15,"sura_number":7,"ayah_number":87,"position":16,"min_x":492.0,"min_y":1534.0,"max_x":582.0,"max_y":1597.0},{"glyph_id":25984,"page_number":161,"line_number":15,"sura_number":7,"ayah_number":87,"position":17,"min_x":486.0,"min_y":1514.0,"max_x":486.0,"max_y":1534.0},{"glyph_id":25985,"page_number":161,"line_number":15,"sura_number":7,"ayah_number":87,"position":18,"min_x":408.0,"min_y":1529.0,"max_x":482.0,"max_y":1599.0},{"glyph_id":25986,"page_number":161,"line_number":15,"sura_number":7,"ayah_number":87,"position":19,"min_x":340.0,"min_y":1534.0,"max_x":408.0,"max_y":1599.0},{"glyph_id":25987,"page_number":161,"line_number":15,"sura_number":7,"ayah_number":87,"position":20,"min_x":144.0,"min_y":1528.0,"max_x":340.0,"max_y":1600.0},{"glyph_id":25988,"page_number":161,"line_number":15,"sura_number":7,"ayah_number":87,"position":21,"min_x":52.0,"min_y":1526.0,"max_x":135.0,"max_y":1602.0}]