[{"glyph_id":27549,"page_number":172,"line_number":1,"sura_number":7,"ayah_number":164,"position":1,"min_x":924.0,"min_y":45.0,"max_x":979.0,"max_y":112.0},{"glyph_id":27550,"page_number":172,"line_number":1,"sura_number":7,"ayah_number":164,"position":2,"min_x":840.0,"min_y":41.0,"max_x":916.0,"max_y":97.0},{"glyph_id":27551,"page_number":172,"line_number":1,"sura_number":7,"ayah_number":164,"position":3,"min_x":770.0,"min_y":31.0,"max_x":831.0,"max_y":95.0},{"glyph_id":27552,"page_number":172,"line_number":1,"sura_number":7,"ayah_number":164,"position":4,"min_x":689.0,"min_y":45.0,"max_x":766.0,"max_y":120.0},{"glyph_id":27553,"page_number":172,"line_number":1,"sura_number":7,"ayah_number":164,"position":5,"min_x":645.0,"min_y":44.0,"max_x":681.0,"max_y":119.0},{"glyph_id":27554,"page_number":172,"line_number":1,"sura_number":7,"ayah_number":164,"position":6,"min_x":528.0,"min_y":34.0,"max_x":637.0,"max_y":108.0},{"glyph_id":27555,"page_number":172,"line_number":1,"sura_number":7,"ayah_number":164,"position":7,"min_x":447.0,"min_y":40.0,"max_x":520.0,"max_y":107.0},{"glyph_id":27556,"page_number":172,"line_number":1,"sura_number":7,"ayah_number":164,"position":8,"min_x":441.0,"min_y":24.0,"max_x":442.0,"max_y":46.0},{"glyph_id":27557,"page_number":172,"line_number":1,"sura_number":7,"ayah_number":164,"position":9,"min_x":381.0,"min_y":45.0,"max_x":438.0,"max_y":96.0},{"glyph_id":27558,"page_number":172,"line_number":1,"sura_number":7,"ayah_number":164,"position":10,"min_x":226.0,"min_y":38.0,"max_x":377.0,"max_y":121.0},{"glyph_id":27559,"page_number":172,"line_number":1,"sura_number":7,"ayah_number":164,"position":11,"min_x":186.0,"min_y":36.0,"max_x":220.0,"max_y":105.0},{"glyph_id":27560,"page_number":172,"line_number":1,"sura_number":7,"ayah_number":164,"position":12,"min_x":56.0,"min_y":42.0,"max_x":185.0,"max_y":114.0},{"glyph_id":27561,"page_number":172,"line_number":2,"sura_number":7,"ayah_number":164,"position":13,"min_x":880.0,"min_y":150.0,"max_x":977.0,"max_y":210.0},{"glyph_id":27562,"page_number":172,"line_number":2,"sura_number":7,"ayah_number":164,"position":14,"min_x":768.0,"min_y":148.0,"max_x":873.0,"max_y":215.0},{"glyph_id":27563,"page_number":172,"line_number":2,"sura_number":7,"ayah_number":164,"position":15,"min_x":763.0,"min_y":127.0,"max_x":765.0,"max_y":148.0},{"glyph_id":27564,"page_number":172,"line_number":2,"sura_number":7,"ayah_number":164,"position":16,"min_x":674.0,"min_y":144.0,"max_x":761.0,"max_y":214.0},{"glyph_id":27565,"page_number":172,"line_number":2,"sura_number":7,"ayah_number":164,"position":17,"min_x":553.0,"min_y":144.0,"max_x":665.0,"max_y":216.0},{"glyph_id":27566,"page_number":172,"line_number":2,"sura_number":7,"ayah_number":164,"position":18,"min_x":496.0,"min_y":147.0,"max_x":543.0,"max_y":220.0},{"glyph_id":27567,"page_number":172,"line_number":2,"sura_number":7,"ayah_number":164,"position":19,"min_x":402.0,"min_y":142.0,"max_x":489.0,"max_y":222.0},{"glyph_id":27568,"page_number":172,"line_number":2,"sura_number":7,"ayah_number":164,"position":20,"min_x":276.0,"min_y":138.0,"max_x":397.0,"max_y":212.0},{"glyph_id":27569,"page_number":172,"line_number":2,"sura_number":7,"ayah_number":164,"position":21,"min_x":162.0,"min_y":144.0,"max_x":275.0,"max_y":216.0},{"glyph_id":27570,"page_number":172,"line_number":2,"sura_number":7,"ayah_number":164,"position":22,"min_x":56.0,"min_y":143.0,"max_x":139.0,"max_y":219.0},{"glyph_id":27571,"page_number":172,"line_number":3,"sura_number":7,"ayah_number":165,"position":1,"min_x":916.0,"min_y":251.0,"max_x":979.0,"max_y":309.0},{"glyph_id":27572,"page_number":172,"line_number":3,"sura_number":7,"ayah_number":165,"position":2,"min_x":833.0,"min_y":257.0,"max_x":906.0,"max_y":322.0},{"glyph_id":27573,"page_number":172,"line_number":3,"sura_number":7,"ayah_number":165,"position":3,"min_x":792.0,"min_y":259.0,"max_x":823.0,"max_y":309.0},{"glyph_id":27574,"page_number":172,"line_number":3,"sura_number":7,"ayah_number":165,"position":4,"min_x":633.0,"min_y":254.0,"max_x":783.0,"max_y":323.0},{"glyph_id":27575,"page_number":172,"line_number":3,"sura_number":7,"ayah_number":165,"position":5,"min_x":573.0,"min_y":283.0,"max_x":621.0,"max_y":330.0},{"glyph_id":27576,"page_number":172,"line_number":3,"sura_number":7,"ayah_number":165,"position":6,"min_x":470.0,"min_y":250.0,"max_x":567.0,"max_y":319.0},{"glyph_id":27577,"page_number":172,"line_number":3,"sura_number":7,"ayah_number":165,"position":7,"min_x":378.0,"min_y":246.0,"max_x":459.0,"max_y":325.0},{"glyph_id":27578,"page_number":172,"line_number":3,"sura_number":7,"ayah_number":165,"position":8,"min_x":214.0,"min_y":261.0,"max_x":367.0,"max_y":324.0},{"glyph_id":27579,"page_number":172,"line_number":3,"sura_number":7,"ayah_number":165,"position":9,"min_x":153.0,"min_y":260.0,"max_x":205.0,"max_y":328.0},{"glyph_id":27580,"page_number":172,"line_number":3,"sura_number":7,"ayah_number":165,"position":10,"min_x":57.0,"min_y":258.0,"max_x":146.0,"max_y":323.0},{"glyph_id":27581,"page_number":172,"line_number":4,"sura_number":7,"ayah_number":165,"position":11,"min_x":868.0,"min_y":359.0,"max_x":975.0,"max_y":425.0},{"glyph_id":27582,"page_number":172,"line_number":4,"sura_number":7,"ayah_number":165,"position":12,"min_x":737.0,"min_y":353.0,"max_x":857.0,"max_y":431.0},{"glyph_id":27583,"page_number":172,"line_number":4,"sura_number":7,"ayah_number":165,"position":13,"min_x":627.0,"min_y":360.0,"max_x":724.0,"max_y":428.0},{"glyph_id":27584,"page_number":172,"line_number":4,"sura_number":7,"ayah_number":165,"position":14,"min_x":508.0,"min_y":362.0,"max_x":621.0,"max_y":448.0},{"glyph_id":27585,"page_number":172,"line_number":4,"sura_number":7,"ayah_number":165,"position":15,"min_x":400.0,"min_y":370.0,"max_x":499.0,"max_y":447.0},{"glyph_id":27586,"page_number":172,"line_number":4,"sura_number":7,"ayah_number":165,"position":16,"min_x":339.0,"min_y":376.0,"max_x":393.0,"max_y":435.0},{"glyph_id":27587,"page_number":172,"line_number":4,"sura_number":7,"ayah_number":165,"position":17,"min_x":252.0,"min_y":361.0,"max_x":320.0,"max_y":428.0},{"glyph_id":27588,"page_number":172,"line_number":4,"sura_number":7,"ayah_number":165,"position":18,"min_x":59.0,"min_y":358.0,"max_x":244.0,"max_y":428.0},{"glyph_id":27589,"page_number":172,"line_number":5,"sura_number":7,"ayah_number":165,"position":19,"min_x":896.0,"min_y":464.0,"max_x":977.0,"max_y":540.0},{"glyph_id":27590,"page_number":172,"line_number":5,"sura_number":7,"ayah_number":166,"position":1,"min_x":827.0,"min_y":466.0,"max_x":897.0,"max_y":523.0},{"glyph_id":27591,"page_number":172,"line_number":5,"sura_number":7,"ayah_number":166,"position":2,"min_x":752.0,"min_y":472.0,"max_x":823.0,"max_y":537.0},{"glyph_id":27592,"page_number":172,"line_number":5,"sura_number":7,"ayah_number":166,"position":3,"min_x":702.0,"min_y":475.0,"max_x":750.0,"max_y":532.0},{"glyph_id":27593,"page_number":172,"line_number":5,"sura_number":7,"ayah_number":166,"position":4,"min_x":668.0,"min_y":473.0,"max_x":697.0,"max_y":523.0},{"glyph_id":27594,"page_number":172,"line_number":5,"sura_number":7,"ayah_number":166,"position":5,"min_x":600.0,"min_y":471.0,"max_x":660.0,"max_y":538.0},{"glyph_id":27595,"page_number":172,"line_number":5,"sura_number":7,"ayah_number":166,"position":6,"min_x":533.0,"min_y":469.0,"max_x":599.0,"max_y":523.0},{"glyph_id":27596,"page_number":172,"line_number":5,"sura_number":7,"ayah_number":166,"position":7,"min_x":478.0,"min_y":466.0,"max_x":533.0,"max_y":524.0},{"glyph_id":27597,"page_number":172,"line_number":5,"sura_number":7,"ayah_number":166,"position":8,"min_x":419.0,"min_y":467.0,"max_x":473.0,"max_y":547.0},{"glyph_id":27598,"page_number":172,"line_number":5,"sura_number":7,"ayah_number":166,"position":9,"min_x":333.0,"min_y":461.0,"max_x":409.0,"max_y":537.0},{"glyph_id":27599,"page_number":172,"line_number":5,"sura_number":7,"ayah_number":166,"position":10,"min_x":247.0,"min_y":468.0,"max_x":331.0,"max_y":540.0},{"glyph_id":27600,"page_number":172,"line_number":5,"sura_number":7,"ayah_number":166,"position":11,"min_x":60.0,"min_y":470.0,"max_x":246.0,"max_y":538.0},{"glyph_id":27601,"page_number":172,"line_number":6,"sura_number":7,"ayah_number":166,"position":12,"min_x":896.0,"min_y":571.0,"max_x":977.0,"max_y":647.0},{"glyph_id":27602,"page_number":172,"line_number":6,"sura_number":7,"ayah_number":167,"position":1,"min_x":833.0,"min_y":577.0,"max_x":897.0,"max_y":647.0},{"glyph_id":27603,"page_number":172,"line_number":6,"sura_number":7,"ayah_number":167,"position":2,"min_x":695.0,"min_y":565.0,"max_x":827.0,"max_y":635.0},{"glyph_id":27604,"page_number":172,"line_number":6,"sura_number":7,"ayah_number":167,"position":3,"min_x":617.0,"min_y":572.0,"max_x":690.0,"max_y":642.0},{"glyph_id":27605,"page_number":172,"line_number":6,"sura_number":7,"ayah_number":167,"position":4,"min_x":505.0,"min_y":572.0,"max_x":609.0,"max_y":642.0},{"glyph_id":27606,"page_number":172,"line_number":6,"sura_number":7,"ayah_number":167,"position":5,"min_x":395.0,"min_y":577.0,"max_x":501.0,"max_y":658.0},{"glyph_id":27607,"page_number":172,"line_number":6,"sura_number":7,"ayah_number":167,"position":6,"min_x":342.0,"min_y":579.0,"max_x":388.0,"max_y":650.0},{"glyph_id":27608,"page_number":172,"line_number":6,"sura_number":7,"ayah_number":167,"position":7,"min_x":265.0,"min_y":583.0,"max_x":334.0,"max_y":648.0},{"glyph_id":27609,"page_number":172,"line_number":6,"sura_number":7,"ayah_number":167,"position":8,"min_x":129.0,"min_y":576.0,"max_x":262.0,"max_y":644.0},{"glyph_id":27610,"page_number":172,"line_number":6,"sura_number":7,"ayah_number":167,"position":9,"min_x":55.0,"min_y":584.0,"max_x":124.0,"max_y":640.0},{"glyph_id":27611,"page_number":172,"line_number":7,"sura_number":7,"ayah_number":167,"position":10,"min_x":838.0,"min_y":687.0,"max_x":979.0,"max_y":764.0},{"glyph_id":27612,"page_number":172,"line_number":7,"sura_number":7,"ayah_number":167,"position":11,"min_x":752.0,"min_y":690.0,"max_x":828.0,"max_y":750.0},{"glyph_id":27613,"page_number":172,"line_number":7,"sura_number":7,"ayah_number":167,"position":12,"min_x":616.0,"min_y":683.0,"max_x":745.0,"max_y":753.0},{"glyph_id":27614,"page_number":172,"line_number":7,"sura_number":7,"ayah_number":167,"position":13,"min_x":607.0,"min_y":682.0,"max_x":609.0,"max_y":703.0},{"glyph_id":27615,"page_number":172,"line_number":7,"sura_number":7,"ayah_number":167,"position":14,"min_x":566.0,"min_y":683.0,"max_x":605.0,"max_y":756.0},{"glyph_id":27616,"page_number":172,"line_number":7,"sura_number":7,"ayah_number":167,"position":15,"min_x":426.0,"min_y":682.0,"max_x":556.0,"max_y":747.0},{"glyph_id":27617,"page_number":172,"line_number":7,"sura_number":7,"ayah_number":167,"position":16,"min_x":294.0,"min_y":685.0,"max_x":415.0,"max_y":764.0},{"glyph_id":27618,"page_number":172,"line_number":7,"sura_number":7,"ayah_number":167,"position":17,"min_x":145.0,"min_y":682.0,"max_x":285.0,"max_y":756.0},{"glyph_id":27619,"page_number":172,"line_number":7,"sura_number":7,"ayah_number":167,"position":18,"min_x":142.0,"min_y":678.0,"max_x":141.0,"max_y":699.0},{"glyph_id":27620,"page_number":172,"line_number":7,"sura_number":7,"ayah_number":167,"position":19,"min_x":56.0,"min_y":681.0,"max_x":137.0,"max_y":755.0},{"glyph_id":27621,"page_number":172,"line_number":8,"sura_number":7,"ayah_number":167,"position":20,"min_x":877.0,"min_y":789.0,"max_x":979.0,"max_y":855.0},{"glyph_id":27622,"page_number":172,"line_number":8,"sura_number":7,"ayah_number":167,"position":21,"min_x":757.0,"min_y":788.0,"max_x":874.0,"max_y":862.0},{"glyph_id":27623,"page_number":172,"line_number":8,"sura_number":7,"ayah_number":167,"position":22,"min_x":668.0,"min_y":785.0,"max_x":750.0,"max_y":861.0},{"glyph_id":27624,"page_number":172,"line_number":8,"sura_number":7,"ayah_number":168,"position":1,"min_x":505.0,"min_y":783.0,"max_x":669.0,"max_y":869.0},{"glyph_id":27625,"page_number":172,"line_number":8,"sura_number":7,"ayah_number":168,"position":2,"min_x":411.0,"min_y":804.0,"max_x":494.0,"max_y":863.0},{"glyph_id":27626,"page_number":172,"line_number":8,"sura_number":7,"ayah_number":168,"position":3,"min_x":281.0,"min_y":784.0,"max_x":401.0,"max_y":860.0},{"glyph_id":27627,"page_number":172,"line_number":8,"sura_number":7,"ayah_number":168,"position":4,"min_x":179.0,"min_y":779.0,"max_x":269.0,"max_y":845.0},{"glyph_id":27628,"page_number":172,"line_number":8,"sura_number":7,"ayah_number":168,"position":5,"min_x":167.0,"min_y":776.0,"max_x":172.0,"max_y":798.0},{"glyph_id":27629,"page_number":172,"line_number":8,"sura_number":7,"ayah_number":168,"position":6,"min_x":57.0,"min_y":796.0,"max_x":168.0,"max_y":857.0},{"glyph_id":27630,"page_number":172,"line_number":9,"sura_number":7,"ayah_number":168,"position":7,"min_x":744.0,"min_y":899.0,"max_x":975.0,"max_y":964.0},{"glyph_id":27631,"page_number":172,"line_number":9,"sura_number":7,"ayah_number":168,"position":8,"min_x":627.0,"min_y":903.0,"max_x":732.0,"max_y":977.0},{"glyph_id":27632,"page_number":172,"line_number":9,"sura_number":7,"ayah_number":168,"position":9,"min_x":548.0,"min_y":900.0,"max_x":613.0,"max_y":959.0},{"glyph_id":27633,"page_number":172,"line_number":9,"sura_number":7,"ayah_number":168,"position":10,"min_x":422.0,"min_y":896.0,"max_x":531.0,"max_y":963.0},{"glyph_id":27634,"page_number":172,"line_number":9,"sura_number":7,"ayah_number":168,"position":11,"min_x":425.0,"min_y":881.0,"max_x":419.0,"max_y":903.0},{"glyph_id":27635,"page_number":172,"line_number":9,"sura_number":7,"ayah_number":168,"position":12,"min_x":255.0,"min_y":899.0,"max_x":415.0,"max_y":979.0},{"glyph_id":27636,"page_number":172,"line_number":9,"sura_number":7,"ayah_number":168,"position":13,"min_x":58.0,"min_y":895.0,"max_x":241.0,"max_y":970.0},{"glyph_id":27637,"page_number":172,"line_number":10,"sura_number":7,"ayah_number":168,"position":14,"min_x":801.0,"min_y":1006.0,"max_x":975.0,"max_y":1080.0},{"glyph_id":27638,"page_number":172,"line_number":10,"sura_number":7,"ayah_number":168,"position":15,"min_x":692.0,"min_y":993.0,"max_x":790.0,"max_y":1084.0},{"glyph_id":27639,"page_number":172,"line_number":10,"sura_number":7,"ayah_number":168,"position":16,"min_x":555.0,"min_y":1008.0,"max_x":685.0,"max_y":1078.0},{"glyph_id":27640,"page_number":172,"line_number":10,"sura_number":7,"ayah_number":168,"position":17,"min_x":466.0,"min_y":999.0,"max_x":548.0,"max_y":1075.0},{"glyph_id":27641,"page_number":172,"line_number":10,"sura_number":7,"ayah_number":169,"position":1,"min_x":349.0,"min_y":1001.0,"max_x":467.0,"max_y":1059.0},{"glyph_id":27642,"page_number":172,"line_number":10,"sura_number":7,"ayah_number":169,"position":2,"min_x":296.0,"min_y":1007.0,"max_x":343.0,"max_y":1075.0},{"glyph_id":27643,"page_number":172,"line_number":10,"sura_number":7,"ayah_number":169,"position":3,"min_x":173.0,"min_y":1006.0,"max_x":290.0,"max_y":1084.0},{"glyph_id":27644,"page_number":172,"line_number":10,"sura_number":7,"ayah_number":169,"position":4,"min_x":57.0,"min_y":1001.0,"max_x":169.0,"max_y":1060.0},{"glyph_id":27645,"page_number":172,"line_number":11,"sura_number":7,"ayah_number":169,"position":5,"min_x":897.0,"min_y":1107.0,"max_x":977.0,"max_y":1186.0},{"glyph_id":27646,"page_number":172,"line_number":11,"sura_number":7,"ayah_number":169,"position":6,"min_x":757.0,"min_y":1112.0,"max_x":887.0,"max_y":1177.0},{"glyph_id":27647,"page_number":172,"line_number":11,"sura_number":7,"ayah_number":169,"position":7,"min_x":627.0,"min_y":1103.0,"max_x":748.0,"max_y":1173.0},{"glyph_id":27648,"page_number":172,"line_number":11,"sura_number":7,"ayah_number":169,"position":8,"min_x":532.0,"min_y":1113.0,"max_x":622.0,"max_y":1178.0},{"glyph_id":27649,"page_number":172,"line_number":11,"sura_number":7,"ayah_number":169,"position":9,"min_x":453.0,"min_y":1112.0,"max_x":525.0,"max_y":1165.0},{"glyph_id":27650,"page_number":172,"line_number":11,"sura_number":7,"ayah_number":169,"position":10,"min_x":345.0,"min_y":1105.0,"max_x":443.0,"max_y":1171.0},{"glyph_id":27651,"page_number":172,"line_number":11,"sura_number":7,"ayah_number":169,"position":11,"min_x":212.0,"min_y":1107.0,"max_x":335.0,"max_y":1182.0},{"glyph_id":27652,"page_number":172,"line_number":11,"sura_number":7,"ayah_number":169,"position":12,"min_x":93.0,"min_y":1112.0,"max_x":204.0,"max_y":1178.0},{"glyph_id":27653,"page_number":172,"line_number":11,"sura_number":7,"ayah_number":169,"position":13,"min_x":55.0,"min_y":1111.0,"max_x":93.0,"max_y":1166.0},{"glyph_id":27654,"page_number":172,"line_number":12,"sura_number":7,"ayah_number":169,"position":14,"min_x":912.0,"min_y":1229.0,"max_x":977.0,"max_y":1291.0},{"glyph_id":27655,"page_number":172,"line_number":12,"sura_number":7,"ayah_number":169,"position":15,"min_x":822.0,"min_y":1209.0,"max_x":904.0,"max_y":1296.0},{"glyph_id":27656,"page_number":172,"line_number":12,"sura_number":7,"ayah_number":169,"position":16,"min_x":741.0,"min_y":1218.0,"max_x":819.0,"max_y":1285.0},{"glyph_id":27657,"page_number":172,"line_number":12,"sura_number":7,"ayah_number":169,"position":17,"min_x":651.0,"min_y":1215.0,"max_x":732.0,"max_y":1284.0},{"glyph_id":27658,"page_number":172,"line_number":12,"sura_number":7,"ayah_number":169,"position":18,"min_x":538.0,"min_y":1211.0,"max_x":648.0,"max_y":1283.0},{"glyph_id":27659,"page_number":172,"line_number":12,"sura_number":7,"ayah_number":169,"position":19,"min_x":537.0,"min_y":1198.0,"max_x":532.0,"max_y":1218.0},{"glyph_id":27660,"page_number":172,"line_number":12,"sura_number":7,"ayah_number":169,"position":20,"min_x":481.0,"min_y":1215.0,"max_x":528.0,"max_y":1282.0},{"glyph_id":27661,"page_number":172,"line_number":12,"sura_number":7,"ayah_number":169,"position":21,"min_x":400.0,"min_y":1219.0,"max_x":479.0,"max_y":1289.0},{"glyph_id":27662,"page_number":172,"line_number":12,"sura_number":7,"ayah_number":169,"position":22,"min_x":308.0,"min_y":1220.0,"max_x":397.0,"max_y":1297.0},{"glyph_id":27663,"page_number":172,"line_number":12,"sura_number":7,"ayah_number":169,"position":23,"min_x":211.0,"min_y":1218.0,"max_x":299.0,"max_y":1290.0},{"glyph_id":27664,"page_number":172,"line_number":12,"sura_number":7,"ayah_number":169,"position":24,"min_x":58.0,"min_y":1221.0,"max_x":204.0,"max_y":1292.0},{"glyph_id":27665,"page_number":172,"line_number":13,"sura_number":7,"ayah_number":169,"position":25,"min_x":947.0,"min_y":1323.0,"max_x":982.0,"max_y":1386.0},{"glyph_id":27666,"page_number":172,"line_number":13,"sura_number":7,"ayah_number":169,"position":26,"min_x":904.0,"min_y":1318.0,"max_x":939.0,"max_y":1382.0},{"glyph_id":27667,"page_number":172,"line_number":13,"sura_number":7,"ayah_number":169,"position":27,"min_x":807.0,"min_y":1322.0,"max_x":901.0,"max_y":1393.0},{"glyph_id":27668,"page_number":172,"line_number":13,"sura_number":7,"ayah_number":169,"position":28,"min_x":743.0,"min_y":1327.0,"max_x":798.0,"max_y":1395.0},{"glyph_id":27669,"page_number":172,"line_number":13,"sura_number":7,"ayah_number":169,"position":29,"min_x":690.0,"min_y":1328.0,"max_x":739.0,"max_y":1391.0},{"glyph_id":27670,"page_number":172,"line_number":13,"sura_number":7,"ayah_number":169,"position":30,"min_x":629.0,"min_y":1317.0,"max_x":679.0,"max_y":1398.0},{"glyph_id":27671,"page_number":172,"line_number":13,"sura_number":7,"ayah_number":169,"position":31,"min_x":531.0,"min_y":1321.0,"max_x":620.0,"max_y":1388.0},{"glyph_id":27672,"page_number":172,"line_number":13,"sura_number":7,"ayah_number":169,"position":32,"min_x":400.0,"min_y":1326.0,"max_x":523.0,"max_y":1391.0},{"glyph_id":27673,"page_number":172,"line_number":13,"sura_number":7,"ayah_number":169,"position":33,"min_x":360.0,"min_y":1332.0,"max_x":391.0,"max_y":1379.0},{"glyph_id":27674,"page_number":172,"line_number":13,"sura_number":7,"ayah_number":169,"position":34,"min_x":298.0,"min_y":1343.0,"max_x":353.0,"max_y":1393.0},{"glyph_id":27675,"page_number":172,"line_number":13,"sura_number":7,"ayah_number":169,"position":35,"min_x":297.0,"min_y":1326.0,"max_x":293.0,"max_y":1348.0},{"glyph_id":27676,"page_number":172,"line_number":13,"sura_number":7,"ayah_number":169,"position":36,"min_x":184.0,"min_y":1317.0,"max_x":289.0,"max_y":1388.0},{"glyph_id":27677,"page_number":172,"line_number":13,"sura_number":7,"ayah_number":169,"position":37,"min_x":55.0,"min_y":1321.0,"max_x":183.0,"max_y":1390.0},{"glyph_id":27678,"page_number":172,"line_number":14,"sura_number":7,"ayah_number":169,"position":38,"min_x":909.0,"min_y":1438.0,"max_x":979.0,"max_y":1500.0},{"glyph_id":27679,"page_number":172,"line_number":14,"sura_number":7,"ayah_number":169,"position":39,"min_x":764.0,"min_y":1425.0,"max_x":903.0,"max_y":1505.0},{"glyph_id":27680,"page_number":172,"line_number":14,"sura_number":7,"ayah_number":169,"position":40,"min_x":667.0,"min_y":1428.0,"max_x":758.0,"max_y":1499.0},{"glyph_id":27681,"page_number":172,"line_number":14,"sura_number":7,"ayah_number":169,"position":41,"min_x":665.0,"min_y":1414.0,"max_x":661.0,"max_y":1435.0},{"glyph_id":27682,"page_number":172,"line_number":14,"sura_number":7,"ayah_number":169,"position":42,"min_x":582.0,"min_y":1428.0,"max_x":657.0,"max_y":1490.0},{"glyph_id":27683,"page_number":172,"line_number":14,"sura_number":7,"ayah_number":169,"position":43,"min_x":454.0,"min_y":1428.0,"max_x":577.0,"max_y":1498.0},{"glyph_id":27684,"page_number":172,"line_number":14,"sura_number":7,"ayah_number":169,"position":44,"min_x":357.0,"min_y":1427.0,"max_x":439.0,"max_y":1503.0},{"glyph_id":27685,"page_number":172,"line_number":14,"sura_number":7,"ayah_number":170,"position":1,"min_x":237.0,"min_y":1423.0,"max_x":358.0,"max_y":1502.0},{"glyph_id":27686,"page_number":172,"line_number":14,"sura_number":7,"ayah_number":170,"position":2,"min_x":57.0,"min_y":1425.0,"max_x":231.0,"max_y":1499.0},{"glyph_id":27687,"page_number":172,"line_number":15,"sura_number":7,"ayah_number":170,"position":3,"min_x":825.0,"min_y":1539.0,"max_x":977.0,"max_y":1615.0},{"glyph_id":27688,"page_number":172,"line_number":15,"sura_number":7,"ayah_number":170,"position":4,"min_x":708.0,"min_y":1530.0,"max_x":820.0,"max_y":1606.0},{"glyph_id":27689,"page_number":172,"line_number":15,"sura_number":7,"ayah_number":170,"position":5,"min_x":577.0,"min_y":1537.0,"max_x":702.0,"max_y":1605.0},{"glyph_id":27690,"page_number":172,"line_number":15,"sura_number":7,"ayah_number":170,"position":6,"min_x":530.0,"min_y":1536.0,"max_x":571.0,"max_y":1612.0},{"glyph_id":27691,"page_number":172,"line_number":15,"sura_number":7,"ayah_number":170,"position":7,"min_x":486.0,"min_y":1538.0,"max_x":520.0,"max_y":1595.0},{"glyph_id":27692,"page_number":172,"line_number":15,"sura_number":7,"ayah_number":170,"position":8,"min_x":385.0,"min_y":1539.0,"max_x":487.0,"max_y":1620.0},{"glyph_id":27693,"page_number":172,"line_number":15,"sura_number":7,"ayah_number":170,"position":9,"min_x":319.0,"min_y":1532.0,"max_x":381.0,"max_y":1608.0},{"glyph_id":27694,"page_number":172,"line_number":15,"sura_number":7,"ayah_number":170,"position":10,"min_x":152.0,"min_y":1538.0,"max_x":320.0,"max_y":1608.0},{"glyph_id":27695,"page_number":172,"line_number":15,"sura_number":7,"ayah_number":170,"position":11,"min_x":56.0,"min_y":1534.0,"max_x":139.0,"max_y":1610.0}]