[{"glyph_id":30389,"page_number":190,"line_number":1,"sura_number":9,"ayah_number":21,"position":1,"min_x":829.0,"min_y":41.0,"max_x":985.0,"max_y":116.0},{"glyph_id":30390,"page_number":190,"line_number":1,"sura_number":9,"ayah_number":21,"position":2,"min_x":703.0,"min_y":34.0,"max_x":815.0,"max_y":101.0},{"glyph_id":30391,"page_number":190,"line_number":1,"sura_number":9,"ayah_number":21,"position":3,"min_x":551.0,"min_y":43.0,"max_x":699.0,"max_y":112.0},{"glyph_id":30392,"page_number":190,"line_number":1,"sura_number":9,"ayah_number":21,"position":4,"min_x":473.0,"min_y":38.0,"max_x":541.0,"max_y":100.0},{"glyph_id":30393,"page_number":190,"line_number":1,"sura_number":9,"ayah_number":21,"position":5,"min_x":322.0,"min_y":42.0,"max_x":460.0,"max_y":114.0},{"glyph_id":30394,"page_number":190,"line_number":1,"sura_number":9,"ayah_number":21,"position":6,"min_x":184.0,"min_y":36.0,"max_x":310.0,"max_y":110.0},{"glyph_id":30395,"page_number":190,"line_number":1,"sura_number":9,"ayah_number":21,"position":7,"min_x":120.0,"min_y":24.0,"max_x":174.0,"max_y":117.0},{"glyph_id":30396,"page_number":190,"line_number":1,"sura_number":9,"ayah_number":21,"position":8,"min_x":45.0,"min_y":41.0,"max_x":108.0,"max_y":107.0},{"glyph_id":30397,"page_number":190,"line_number":2,"sura_number":9,"ayah_number":21,"position":9,"min_x":892.0,"min_y":148.0,"max_x":984.0,"max_y":213.0},{"glyph_id":30398,"page_number":190,"line_number":2,"sura_number":9,"ayah_number":21,"position":10,"min_x":776.0,"min_y":140.0,"max_x":888.0,"max_y":210.0},{"glyph_id":30399,"page_number":190,"line_number":2,"sura_number":9,"ayah_number":21,"position":11,"min_x":682.0,"min_y":138.0,"max_x":763.0,"max_y":214.0},{"glyph_id":30400,"page_number":190,"line_number":2,"sura_number":9,"ayah_number":22,"position":1,"min_x":494.0,"min_y":147.0,"max_x":683.0,"max_y":212.0},{"glyph_id":30401,"page_number":190,"line_number":2,"sura_number":9,"ayah_number":22,"position":2,"min_x":425.0,"min_y":145.0,"max_x":487.0,"max_y":215.0},{"glyph_id":30402,"page_number":190,"line_number":2,"sura_number":9,"ayah_number":22,"position":3,"min_x":357.0,"min_y":136.0,"max_x":422.0,"max_y":206.0},{"glyph_id":30403,"page_number":190,"line_number":2,"sura_number":9,"ayah_number":22,"position":4,"min_x":345.0,"min_y":127.0,"max_x":350.0,"max_y":147.0},{"glyph_id":30404,"page_number":190,"line_number":2,"sura_number":9,"ayah_number":22,"position":5,"min_x":307.0,"min_y":140.0,"max_x":346.0,"max_y":215.0},{"glyph_id":30405,"page_number":190,"line_number":2,"sura_number":9,"ayah_number":22,"position":6,"min_x":249.0,"min_y":144.0,"max_x":301.0,"max_y":199.0},{"glyph_id":30406,"page_number":190,"line_number":2,"sura_number":9,"ayah_number":22,"position":7,"min_x":135.0,"min_y":146.0,"max_x":243.0,"max_y":206.0},{"glyph_id":30407,"page_number":190,"line_number":2,"sura_number":9,"ayah_number":22,"position":8,"min_x":52.0,"min_y":140.0,"max_x":130.0,"max_y":207.0},{"glyph_id":30408,"page_number":190,"line_number":3,"sura_number":9,"ayah_number":22,"position":9,"min_x":861.0,"min_y":257.0,"max_x":980.0,"max_y":317.0},{"glyph_id":30409,"page_number":190,"line_number":3,"sura_number":9,"ayah_number":22,"position":10,"min_x":765.0,"min_y":245.0,"max_x":846.0,"max_y":321.0},{"glyph_id":30410,"page_number":190,"line_number":3,"sura_number":9,"ayah_number":23,"position":1,"min_x":666.0,"min_y":245.0,"max_x":766.0,"max_y":319.0},{"glyph_id":30411,"page_number":190,"line_number":3,"sura_number":9,"ayah_number":23,"position":2,"min_x":527.0,"min_y":239.0,"max_x":650.0,"max_y":318.0},{"glyph_id":30412,"page_number":190,"line_number":3,"sura_number":9,"ayah_number":23,"position":3,"min_x":405.0,"min_y":253.0,"max_x":517.0,"max_y":318.0},{"glyph_id":30413,"page_number":190,"line_number":3,"sura_number":9,"ayah_number":23,"position":4,"min_x":355.0,"min_y":247.0,"max_x":390.0,"max_y":306.0},{"glyph_id":30414,"page_number":190,"line_number":3,"sura_number":9,"ayah_number":23,"position":5,"min_x":217.0,"min_y":245.0,"max_x":354.0,"max_y":314.0},{"glyph_id":30415,"page_number":190,"line_number":3,"sura_number":9,"ayah_number":23,"position":6,"min_x":52.0,"min_y":240.0,"max_x":208.0,"max_y":331.0},{"glyph_id":30416,"page_number":190,"line_number":4,"sura_number":9,"ayah_number":23,"position":7,"min_x":811.0,"min_y":349.0,"max_x":982.0,"max_y":439.0},{"glyph_id":30417,"page_number":190,"line_number":4,"sura_number":9,"ayah_number":23,"position":8,"min_x":678.0,"min_y":351.0,"max_x":794.0,"max_y":434.0},{"glyph_id":30418,"page_number":190,"line_number":4,"sura_number":9,"ayah_number":23,"position":9,"min_x":626.0,"min_y":369.0,"max_x":666.0,"max_y":428.0},{"glyph_id":30419,"page_number":190,"line_number":4,"sura_number":9,"ayah_number":23,"position":10,"min_x":463.0,"min_y":357.0,"max_x":616.0,"max_y":425.0},{"glyph_id":30420,"page_number":190,"line_number":4,"sura_number":9,"ayah_number":23,"position":11,"min_x":277.0,"min_y":353.0,"max_x":446.0,"max_y":425.0},{"glyph_id":30421,"page_number":190,"line_number":4,"sura_number":9,"ayah_number":23,"position":12,"min_x":222.0,"min_y":357.0,"max_x":279.0,"max_y":425.0},{"glyph_id":30422,"page_number":190,"line_number":4,"sura_number":9,"ayah_number":23,"position":13,"min_x":56.0,"min_y":356.0,"max_x":215.0,"max_y":437.0},{"glyph_id":30423,"page_number":190,"line_number":4,"sura_number":9,"ayah_number":23,"position":14,"min_x":58.0,"min_y":359.0,"max_x":53.0,"max_y":379.0},{"glyph_id":30424,"page_number":190,"line_number":5,"sura_number":9,"ayah_number":23,"position":15,"min_x":911.0,"min_y":472.0,"max_x":987.0,"max_y":530.0},{"glyph_id":30425,"page_number":190,"line_number":5,"sura_number":9,"ayah_number":23,"position":16,"min_x":777.0,"min_y":455.0,"max_x":903.0,"max_y":533.0},{"glyph_id":30426,"page_number":190,"line_number":5,"sura_number":9,"ayah_number":23,"position":17,"min_x":678.0,"min_y":459.0,"max_x":774.0,"max_y":546.0},{"glyph_id":30427,"page_number":190,"line_number":5,"sura_number":9,"ayah_number":23,"position":18,"min_x":539.0,"min_y":450.0,"max_x":668.0,"max_y":535.0},{"glyph_id":30428,"page_number":190,"line_number":5,"sura_number":9,"ayah_number":23,"position":19,"min_x":467.0,"min_y":469.0,"max_x":525.0,"max_y":542.0},{"glyph_id":30429,"page_number":190,"line_number":5,"sura_number":9,"ayah_number":23,"position":20,"min_x":250.0,"min_y":459.0,"max_x":458.0,"max_y":532.0},{"glyph_id":30430,"page_number":190,"line_number":5,"sura_number":9,"ayah_number":23,"position":21,"min_x":150.0,"min_y":459.0,"max_x":232.0,"max_y":535.0},{"glyph_id":30431,"page_number":190,"line_number":5,"sura_number":9,"ayah_number":24,"position":1,"min_x":88.0,"min_y":460.0,"max_x":151.0,"max_y":529.0},{"glyph_id":30432,"page_number":190,"line_number":5,"sura_number":9,"ayah_number":24,"position":2,"min_x":45.0,"min_y":482.0,"max_x":81.0,"max_y":536.0},{"glyph_id":30433,"page_number":190,"line_number":6,"sura_number":9,"ayah_number":24,"position":3,"min_x":907.0,"min_y":572.0,"max_x":981.0,"max_y":628.0},{"glyph_id":30434,"page_number":190,"line_number":6,"sura_number":9,"ayah_number":24,"position":4,"min_x":758.0,"min_y":569.0,"max_x":899.0,"max_y":654.0},{"glyph_id":30435,"page_number":190,"line_number":6,"sura_number":9,"ayah_number":24,"position":5,"min_x":541.0,"min_y":564.0,"max_x":748.0,"max_y":652.0},{"glyph_id":30436,"page_number":190,"line_number":6,"sura_number":9,"ayah_number":24,"position":6,"min_x":361.0,"min_y":568.0,"max_x":529.0,"max_y":655.0},{"glyph_id":30437,"page_number":190,"line_number":6,"sura_number":9,"ayah_number":24,"position":7,"min_x":205.0,"min_y":565.0,"max_x":353.0,"max_y":637.0},{"glyph_id":30438,"page_number":190,"line_number":6,"sura_number":9,"ayah_number":24,"position":8,"min_x":49.0,"min_y":565.0,"max_x":206.0,"max_y":638.0},{"glyph_id":30439,"page_number":190,"line_number":7,"sura_number":9,"ayah_number":24,"position":9,"min_x":872.0,"min_y":666.0,"max_x":980.0,"max_y":745.0},{"glyph_id":30440,"page_number":190,"line_number":7,"sura_number":9,"ayah_number":24,"position":10,"min_x":634.0,"min_y":675.0,"max_x":854.0,"max_y":746.0},{"glyph_id":30441,"page_number":190,"line_number":7,"sura_number":9,"ayah_number":24,"position":11,"min_x":488.0,"min_y":675.0,"max_x":618.0,"max_y":744.0},{"glyph_id":30442,"page_number":190,"line_number":7,"sura_number":9,"ayah_number":24,"position":12,"min_x":364.0,"min_y":673.0,"max_x":478.0,"max_y":746.0},{"glyph_id":30443,"page_number":190,"line_number":7,"sura_number":9,"ayah_number":24,"position":13,"min_x":222.0,"min_y":676.0,"max_x":352.0,"max_y":732.0},{"glyph_id":30444,"page_number":190,"line_number":7,"sura_number":9,"ayah_number":24,"position":14,"min_x":50.0,"min_y":672.0,"max_x":208.0,"max_y":744.0},{"glyph_id":30445,"page_number":190,"line_number":8,"sura_number":9,"ayah_number":24,"position":15,"min_x":805.0,"min_y":784.0,"max_x":982.0,"max_y":855.0},{"glyph_id":30446,"page_number":190,"line_number":8,"sura_number":9,"ayah_number":24,"position":16,"min_x":699.0,"min_y":775.0,"max_x":793.0,"max_y":850.0},{"glyph_id":30447,"page_number":190,"line_number":8,"sura_number":9,"ayah_number":24,"position":17,"min_x":521.0,"min_y":782.0,"max_x":688.0,"max_y":865.0},{"glyph_id":30448,"page_number":190,"line_number":8,"sura_number":9,"ayah_number":24,"position":18,"min_x":413.0,"min_y":795.0,"max_x":505.0,"max_y":855.0},{"glyph_id":30449,"page_number":190,"line_number":8,"sura_number":9,"ayah_number":24,"position":19,"min_x":349.0,"min_y":785.0,"max_x":404.0,"max_y":856.0},{"glyph_id":30450,"page_number":190,"line_number":8,"sura_number":9,"ayah_number":24,"position":20,"min_x":193.0,"min_y":786.0,"max_x":336.0,"max_y":851.0},{"glyph_id":30451,"page_number":190,"line_number":8,"sura_number":9,"ayah_number":24,"position":21,"min_x":49.0,"min_y":788.0,"max_x":186.0,"max_y":859.0},{"glyph_id":30452,"page_number":190,"line_number":9,"sura_number":9,"ayah_number":24,"position":22,"min_x":950.0,"min_y":908.0,"max_x":986.0,"max_y":962.0},{"glyph_id":30453,"page_number":190,"line_number":9,"sura_number":9,"ayah_number":24,"position":23,"min_x":815.0,"min_y":897.0,"max_x":942.0,"max_y":967.0},{"glyph_id":30454,"page_number":190,"line_number":9,"sura_number":9,"ayah_number":24,"position":24,"min_x":667.0,"min_y":886.0,"max_x":808.0,"max_y":961.0},{"glyph_id":30455,"page_number":190,"line_number":9,"sura_number":9,"ayah_number":24,"position":25,"min_x":589.0,"min_y":890.0,"max_x":658.0,"max_y":961.0},{"glyph_id":30456,"page_number":190,"line_number":9,"sura_number":9,"ayah_number":24,"position":26,"min_x":464.0,"min_y":881.0,"max_x":580.0,"max_y":959.0},{"glyph_id":30457,"page_number":190,"line_number":9,"sura_number":9,"ayah_number":24,"position":27,"min_x":396.0,"min_y":894.0,"max_x":454.0,"max_y":947.0},{"glyph_id":30458,"page_number":190,"line_number":9,"sura_number":9,"ayah_number":24,"position":28,"min_x":290.0,"min_y":882.0,"max_x":393.0,"max_y":967.0},{"glyph_id":30459,"page_number":190,"line_number":9,"sura_number":9,"ayah_number":24,"position":29,"min_x":291.0,"min_y":892.0,"max_x":290.0,"max_y":913.0},{"glyph_id":30460,"page_number":190,"line_number":9,"sura_number":9,"ayah_number":24,"position":30,"min_x":210.0,"min_y":891.0,"max_x":286.0,"max_y":957.0},{"glyph_id":30461,"page_number":190,"line_number":9,"sura_number":9,"ayah_number":24,"position":31,"min_x":163.0,"min_y":887.0,"max_x":200.0,"max_y":947.0},{"glyph_id":30462,"page_number":190,"line_number":9,"sura_number":9,"ayah_number":24,"position":32,"min_x":53.0,"min_y":895.0,"max_x":159.0,"max_y":960.0},{"glyph_id":30463,"page_number":190,"line_number":10,"sura_number":9,"ayah_number":24,"position":33,"min_x":893.0,"min_y":997.0,"max_x":984.0,"max_y":1081.0},{"glyph_id":30464,"page_number":190,"line_number":10,"sura_number":9,"ayah_number":24,"position":34,"min_x":653.0,"min_y":997.0,"max_x":879.0,"max_y":1068.0},{"glyph_id":30465,"page_number":190,"line_number":10,"sura_number":9,"ayah_number":24,"position":35,"min_x":548.0,"min_y":994.0,"max_x":630.0,"max_y":1070.0},{"glyph_id":30466,"page_number":190,"line_number":10,"sura_number":9,"ayah_number":25,"position":1,"min_x":466.0,"min_y":995.0,"max_x":549.0,"max_y":1054.0},{"glyph_id":30467,"page_number":190,"line_number":10,"sura_number":9,"ayah_number":25,"position":2,"min_x":270.0,"min_y":999.0,"max_x":457.0,"max_y":1081.0},{"glyph_id":30468,"page_number":190,"line_number":10,"sura_number":9,"ayah_number":25,"position":3,"min_x":209.0,"min_y":1002.0,"max_x":263.0,"max_y":1055.0},{"glyph_id":30469,"page_number":190,"line_number":10,"sura_number":9,"ayah_number":25,"position":4,"min_x":169.0,"min_y":1013.0,"max_x":205.0,"max_y":1068.0},{"glyph_id":30470,"page_number":190,"line_number":10,"sura_number":9,"ayah_number":25,"position":5,"min_x":51.0,"min_y":1002.0,"max_x":160.0,"max_y":1067.0},{"glyph_id":30471,"page_number":190,"line_number":11,"sura_number":9,"ayah_number":25,"position":6,"min_x":826.0,"min_y":1103.0,"max_x":986.0,"max_y":1177.0},{"glyph_id":30472,"page_number":190,"line_number":11,"sura_number":9,"ayah_number":25,"position":7,"min_x":826.0,"min_y":1097.0,"max_x":823.0,"max_y":1118.0},{"glyph_id":30473,"page_number":190,"line_number":11,"sura_number":9,"ayah_number":25,"position":8,"min_x":737.0,"min_y":1110.0,"max_x":819.0,"max_y":1187.0},{"glyph_id":30474,"page_number":190,"line_number":11,"sura_number":9,"ayah_number":25,"position":9,"min_x":611.0,"min_y":1108.0,"max_x":727.0,"max_y":1184.0},{"glyph_id":30475,"page_number":190,"line_number":11,"sura_number":9,"ayah_number":25,"position":10,"min_x":608.0,"min_y":1100.0,"max_x":606.0,"max_y":1121.0},{"glyph_id":30476,"page_number":190,"line_number":11,"sura_number":9,"ayah_number":25,"position":11,"min_x":570.0,"min_y":1110.0,"max_x":602.0,"max_y":1178.0},{"glyph_id":30477,"page_number":190,"line_number":11,"sura_number":9,"ayah_number":25,"position":12,"min_x":306.0,"min_y":1096.0,"max_x":554.0,"max_y":1189.0},{"glyph_id":30478,"page_number":190,"line_number":11,"sura_number":9,"ayah_number":25,"position":13,"min_x":105.0,"min_y":1103.0,"max_x":284.0,"max_y":1190.0},{"glyph_id":30479,"page_number":190,"line_number":11,"sura_number":9,"ayah_number":25,"position":14,"min_x":52.0,"min_y":1104.0,"max_x":93.0,"max_y":1198.0},{"glyph_id":30480,"page_number":190,"line_number":12,"sura_number":9,"ayah_number":25,"position":15,"min_x":902.0,"min_y":1206.0,"max_x":981.0,"max_y":1290.0},{"glyph_id":30481,"page_number":190,"line_number":12,"sura_number":9,"ayah_number":25,"position":16,"min_x":712.0,"min_y":1214.0,"max_x":887.0,"max_y":1292.0},{"glyph_id":30482,"page_number":190,"line_number":12,"sura_number":9,"ayah_number":25,"position":17,"min_x":608.0,"min_y":1212.0,"max_x":695.0,"max_y":1278.0},{"glyph_id":30483,"page_number":190,"line_number":12,"sura_number":9,"ayah_number":25,"position":18,"min_x":443.0,"min_y":1212.0,"max_x":598.0,"max_y":1277.0},{"glyph_id":30484,"page_number":190,"line_number":12,"sura_number":9,"ayah_number":25,"position":19,"min_x":236.0,"min_y":1210.0,"max_x":425.0,"max_y":1294.0},{"glyph_id":30485,"page_number":190,"line_number":12,"sura_number":9,"ayah_number":25,"position":20,"min_x":52.0,"min_y":1203.0,"max_x":232.0,"max_y":1279.0},{"glyph_id":30486,"page_number":190,"line_number":13,"sura_number":9,"ayah_number":25,"position":21,"min_x":917.0,"min_y":1327.0,"max_x":986.0,"max_y":1393.0},{"glyph_id":30487,"page_number":190,"line_number":13,"sura_number":9,"ayah_number":25,"position":22,"min_x":788.0,"min_y":1320.0,"max_x":911.0,"max_y":1386.0},{"glyph_id":30488,"page_number":190,"line_number":13,"sura_number":9,"ayah_number":25,"position":23,"min_x":739.0,"min_y":1315.0,"max_x":779.0,"max_y":1408.0},{"glyph_id":30489,"page_number":190,"line_number":13,"sura_number":9,"ayah_number":25,"position":24,"min_x":620.0,"min_y":1305.0,"max_x":733.0,"max_y":1405.0},{"glyph_id":30490,"page_number":190,"line_number":13,"sura_number":9,"ayah_number":25,"position":25,"min_x":449.0,"min_y":1313.0,"max_x":615.0,"max_y":1398.0},{"glyph_id":30491,"page_number":190,"line_number":13,"sura_number":9,"ayah_number":25,"position":26,"min_x":364.0,"min_y":1315.0,"max_x":446.0,"max_y":1391.0},{"glyph_id":30492,"page_number":190,"line_number":13,"sura_number":9,"ayah_number":26,"position":1,"min_x":306.0,"min_y":1316.0,"max_x":365.0,"max_y":1402.0},{"glyph_id":30493,"page_number":190,"line_number":13,"sura_number":9,"ayah_number":26,"position":2,"min_x":244.0,"min_y":1313.0,"max_x":304.0,"max_y":1388.0},{"glyph_id":30494,"page_number":190,"line_number":13,"sura_number":9,"ayah_number":26,"position":3,"min_x":189.0,"min_y":1321.0,"max_x":241.0,"max_y":1374.0},{"glyph_id":30495,"page_number":190,"line_number":13,"sura_number":9,"ayah_number":26,"position":4,"min_x":51.0,"min_y":1319.0,"max_x":188.0,"max_y":1389.0},{"glyph_id":30496,"page_number":190,"line_number":14,"sura_number":9,"ayah_number":26,"position":5,"min_x":929.0,"min_y":1431.0,"max_x":983.0,"max_y":1494.0},{"glyph_id":30497,"page_number":190,"line_number":14,"sura_number":9,"ayah_number":26,"position":6,"min_x":783.0,"min_y":1431.0,"max_x":920.0,"max_y":1494.0},{"glyph_id":30498,"page_number":190,"line_number":14,"sura_number":9,"ayah_number":26,"position":7,"min_x":694.0,"min_y":1425.0,"max_x":774.0,"max_y":1492.0},{"glyph_id":30499,"page_number":190,"line_number":14,"sura_number":9,"ayah_number":26,"position":8,"min_x":467.0,"min_y":1425.0,"max_x":686.0,"max_y":1497.0},{"glyph_id":30500,"page_number":190,"line_number":14,"sura_number":9,"ayah_number":26,"position":9,"min_x":341.0,"min_y":1420.0,"max_x":452.0,"max_y":1495.0},{"glyph_id":30501,"page_number":190,"line_number":14,"sura_number":9,"ayah_number":26,"position":10,"min_x":236.0,"min_y":1424.0,"max_x":335.0,"max_y":1492.0},{"glyph_id":30502,"page_number":190,"line_number":14,"sura_number":9,"ayah_number":26,"position":11,"min_x":186.0,"min_y":1415.0,"max_x":220.0,"max_y":1493.0},{"glyph_id":30503,"page_number":190,"line_number":14,"sura_number":9,"ayah_number":26,"position":12,"min_x":49.0,"min_y":1425.0,"max_x":179.0,"max_y":1495.0},{"glyph_id":30504,"page_number":190,"line_number":15,"sura_number":9,"ayah_number":26,"position":13,"min_x":852.0,"min_y":1523.0,"max_x":984.0,"max_y":1598.0},{"glyph_id":30505,"page_number":190,"line_number":15,"sura_number":9,"ayah_number":26,"position":14,"min_x":695.0,"min_y":1521.0,"max_x":840.0,"max_y":1600.0},{"glyph_id":30506,"page_number":190,"line_number":15,"sura_number":9,"ayah_number":26,"position":15,"min_x":588.0,"min_y":1529.0,"max_x":684.0,"max_y":1602.0},{"glyph_id":30507,"page_number":190,"line_number":15,"sura_number":9,"ayah_number":26,"position":16,"min_x":581.0,"min_y":1513.0,"max_x":579.0,"max_y":1533.0},{"glyph_id":30508,"page_number":190,"line_number":15,"sura_number":9,"ayah_number":26,"position":17,"min_x":436.0,"min_y":1531.0,"max_x":575.0,"max_y":1600.0},{"glyph_id":30509,"page_number":190,"line_number":15,"sura_number":9,"ayah_number":26,"position":18,"min_x":340.0,"min_y":1531.0,"max_x":426.0,"max_y":1600.0},{"glyph_id":30510,"page_number":190,"line_number":15,"sura_number":9,"ayah_number":26,"position":19,"min_x":159.0,"min_y":1529.0,"max_x":332.0,"max_y":1612.0},{"glyph_id":30511,"page_number":190,"line_number":15,"sura_number":9,"ayah_number":26,"position":20,"min_x":50.0,"min_y":1529.0,"max_x":133.0,"max_y":1605.0}]